{
  "app_id": 2040,
  "app_hash": "b18441a1ff607e10a989891a5462e627",
  "sdk": "Windows 11",
  "device": "FX506LH-HN258T",
  "app_version": "5.6.3 x64",
  "lang_pack": "en",
  "system_lang_pack": "en-US",
  "username": null,
  "first_name": "\ud83d\udc49\ud83e\udd29\ud83c\udf1b\u041a\u0430\u0440\u0430\u0441\u0438\u043a\ud83c\udf1c\ud83e\udd29\ud83d\udc48",
  "last_name": null,
  "full_name": "\ud83d\udc49\ud83e\udd29\ud83c\udf1b\u041a\u0430\u0440\u0430\u0441\u0438\u043a\ud83c\udf1c\ud83e\udd29\ud83d\udc48",
  "is_premium": false,
  "twoFA": "rabotata1234",
  "session_file": "79009129042",
  "phone": "79009129042",
  "id": 6521713183,
  "proxy": [
    3,
    "185.162.130.85",
    10455,
    true,
    "1wqTc9R7StsrTKYSSXJu",
    "RNW78Fm5"
  ],
  "ipv6": false,
  "module": "panel",
  "time": "06:31:17(22.10.24)",
  "status": "Free"
}